LICENSE
README.md
setup.py
UL0d3R.egg-info/PKG-INFO
UL0d3R.egg-info/SOURCES.txt
UL0d3R.egg-info/dependency_links.txt
UL0d3R.egg-info/requires.txt
UL0d3R.egg-info/top_level.txt
UL0d3Rlib/__init__.py