Metadata-Version: 2.1
Name: UL0d3R
Version: 1.0
Summary: Obter informações de Videos dos seus cursos da udemy.
Author: Paulocesar0073
Author-email: 
License: MIT License
Keywords: udemy
License-File: LICENSE
